edcpy/__init__.py
edcpy/backend.py
edcpy/config.py
edcpy/edc_api.py
edcpy/keycloak.py
edcpy/message_handler.py
edcpy/messaging.py
edcpy/models/__init__.py
edcpy/models/asset.py
edcpy/models/contract_definition.py
edcpy/models/contract_negotiation.py
edcpy/models/data_plane_instance.py
edcpy/models/policy_definition.py
edcpy/models/transfer_process.py
edcpy/utils.py
edcpy-0.10.3.dist-info/METADATA
edcpy-0.10.3.dist-info/WHEEL
edcpy-0.10.3.dist-info/entry_points.txt
edcpy-0.10.3.dist-info/RECORD
