Metadata-Version: 2.1
Name: edcpy
Version: 0.10.3
Summary: Package that provides a series of utilities to facilitate interaction with the Management and Control APIs of an EDC connector
License: EUPL-1.2
Author: Andres Garcia Mangas
Author-email: andres.garcia@fundacionctic.org
Requires-Python: >=3.8,<4.0
Classifier: License :: OSI Approved :: European Union Public Licence 1.2 (EUPL 1.2)
Classifier: Programming Language :: Python :: 3
Classifier: Programming Language :: Python :: 3.8
Classifier: Programming Language :: Python :: 3.9
Classifier: Programming Language :: Python :: 3.10
Classifier: Programming Language :: Python :: 3.11
Requires-Dist: coloredlogs (>=15.0.1)
Requires-Dist: cryptography (>=41.0.1)
Requires-Dist: deepmerge (>=1.1.0)
Requires-Dist: environ-config (>=23.2.0)
Requires-Dist: fastapi[all] (>=0.109.0)
Requires-Dist: faststream[rabbit] (>=0.5.34)
Requires-Dist: httpx (>=0.27.0)
Requires-Dist: pydantic (>=2.10.0)
Requires-Dist: pyjwt[crypto] (>=2.7.0)
Requires-Dist: python-slugify (>=8.0.1)
Requires-Dist: requests (>=2.31.0)
